{
  "products": [
    {
      "thumbnail": "https://savani.vn/images/products/2023/10/27/large/ao-thun-co-co-ngan-tay-MPC014S3-2-C03.jpg",
      "title": "hhh",
      "price": 777,
      "description": "gggggg",
      "discountPercentage": "ggggggg",
      "stock": "5",
      "rating": "3",
      "category": "PC",
      "id": 37
    },
    {
      "thumbnail": "https://cdn.tgdd.vn/Products/Images/44/303499/msi-gaming-gf63-thin-11uc-i5-1230vn-thumb-600x600.jpg ",
      "title": "Sản phẩm 2",
      "price": 800,
      "description": "đẹp tt",
      "discountPercentage": "10",
      "stock": "60",
      "rating": "3",
      "category": "Điện thoại",
      "id": 38
    }
  ],
  "users": []
}